{
    "users": [
    {
      "id": 1,
      "name": "rajat",
      "username": "rajatsah",
      "password": "88888888",
      "email": "rajatsah95@gmail.com",
      "mobile": "8544255945"
    },
    {
      "name": "Saifuddin",
      "username": "Saifuddin",
      "password": "123456789",
      "email": "saifuddin2k17@gmail.com",
      "mobile": "9851902688",
      "id": 2
    }
   
  ],
  
    "articles": [
      {
        "id": 1,
        "authorImage": "https://encrypted-tbn0.gstatic.com/images?q=tbn:ANd9GcQ3wDZLZ6BecUn5rtnNEkkrApwxwhffoGGZlA&s",
        "authorName": "Jane Wilde",
        "publicationName": "Tech Insights",
        "publicationDate": "06-01-2024",
        "articleTitle": "The Future of AI in Healthcare",
        "content": "The future of AI in healthcare holds immense potential for transforming both diagnostics and treatment, offering improvements in accuracy, efficiency, and personalization. Here’s an in-depth look at how AI is reshaping these critical areas: Transforming Diagnostics Medical Imaging and Radiology: Enhanced Image Analysis: AI algorithms, particularly deep learning models, can analyze medical images (X-rays, MRIs, CT scans) with high precision. These models can detect anomalies such as tumors, fractures, and other pathologies often earlier and more accurately than human radiologists. Reduction in Diagnostic Errors: AI reduces the likelihood of human error by providing a second opinion or highlighting areas of concern that might be overlooked. Pathology: Digital Pathology: AI can analyze digitized pathology slides, identifying cancerous cells and other abnormalities with high accuracy. This speeds up the diagnostic process and ensures consistent results. Genomics: Genetic Data Analysis: AI helps in interpreting complex genomic data, identifying mutations, and predicting disease risk based on genetic profiles. This aids in early diagnosis and personalized treatment plans. Predictive Analytics: Risk Stratification: AI models analyze patient data to predict the risk of developing certain diseases, enabling preventive measures. For instance, predicting the likelihood of heart disease or diabetes based on lifestyle, genetic, and medical history. Revolutionizing Treatment Personalized Medicine: Tailored Treatment Plans: AI uses patient data, including genetic information, to tailor treatment plans to individual patients. This personalized approach increases the efficacy of treatments and reduces adverse effects. Drug Development: AI accelerates drug discovery by predicting how different compounds will interact with targets in the body. This reduces the time and cost associated with bringing new drugs to market. Robotic Surgery: Precision and Minimally Invasive Procedures: AI-powered robotic systems enhance the precision of surgical procedures, leading to minimally invasive surgeries with quicker recovery times and reduced complications. Training and Simulation: AI provides advanced simulation tools for training surgeons, improving their skills and reducing the risk of errors in actual surgeries.",
        "articleImage": "https://picsum.photos/id/1/250/150",
        "articleType": "Technology"
      },
      {
        "id": 2,
        "authorImage": "https://www.davidchang.ca/wp-content/uploads/2020/09/David-Chang-Photography-Headshots-Toronto-61.jpg",
        "authorName": "Dek Sem",
        "publicationName": "Tech World",
        "publicationDate": "06-02-2024",
        "articleTitle": "Advancements in Web Development",
        "content": "Web development has seen significant advancements in recent years, driven by emerging technologies and changing user expectations. Here's a look at some of the key trends reshaping the field: Progressive Web Apps: Progressive Web Apps (PWAs) are web applications that offer an app-like experience. They combine the best of both web and mobile apps, providing fast loading times, offline functionality, and push notifications. PWAs are becoming increasingly popular as they enhance user engagement and offer seamless experiences across devices. Single Page Applications: Single Page Applications (SPAs) have revolutionized web development by providing dynamic, fast-loading web pages that update content without requiring a full page reload. Technologies like React, Angular, and Vue.js are widely used for building SPAs, enabling developers to create highly interactive user interfaces. Serverless Architecture: Serverless architecture allows developers to build and deploy applications without managing server infrastructure. With services like AWS Lambda, Azure Functions, and Google Cloud Functions, developers can focus on writing code while the cloud provider handles scaling and server management. This approach reduces operational complexity and costs. JAMstack: JAMstack (JavaScript, APIs, and Markup) is a modern web development architecture that decouples the front end from the back end. By using static site generators and content delivery networks (CDNs), JAMstack sites deliver fast, secure, and scalable web experiences. This architecture is gaining traction for its simplicity and performance benefits. WebAssembly: WebAssembly (Wasm) is a binary instruction format that allows code written in languages like C, C++, and Rust to run in the browser at near-native speed. WebAssembly is opening up new possibilities for web development, enabling complex applications like games and video editors to run smoothly in the browser. The future of web development is exciting, with these advancements driving innovation and improving user experiences.",
        "articleImage": "https://picsum.photos/id/2/250/150",
        "articleType": "Web Development"
      },
      {
        "id": 3,
        "authorImage": "https://images.pexels.com/photos/2182970/pexels-photo-2182970.jpeg?cs=srgb&dl=pexels-linkedin-2182970.jpg&fm=jpg",
        "authorName": "Farah Sen",
        "publicationName": "Innovation Daily",
        "publicationDate": "06-03-2024",
        "articleTitle": "React's Role in Modern Web Applications",
        "content": "React has become a cornerstone of modern web applications, offering a robust framework for building dynamic and interactive user interfaces. Here's an in-depth look at how React is transforming web development: Component-Based Architecture: React's component-based architecture allows developers to build encapsulated components that manage their own state. This modular approach promotes reusability and makes it easier to maintain and scale applications. Virtual DOM: React's Virtual DOM is a lightweight copy of the actual DOM. When the state of an application changes, React updates the Virtual DOM first and then efficiently syncs it with the real DOM. This process minimizes expensive DOM manipulations and enhances performance. Hooks: React Hooks introduced a new way to manage state and side effects in functional components. With hooks like useState, useEffect, and useContext, developers can write cleaner and more concise code, reducing the reliance on class components. Ecosystem and Community: React has a vibrant ecosystem with a wide range of libraries, tools, and extensions. The large and active community contributes to the continuous evolution of React, providing support and resources for developers. React Native: React Native extends React's capabilities to mobile app development. By using the same principles and components, developers can build cross-platform mobile apps with a single codebase, saving time and effort. Server-Side Rendering: Server-Side Rendering (SSR) with React improves performance and SEO by rendering pages on the server before sending them to the client. Frameworks like Next.js make it easier to implement SSR in React applications. The adoption of React in modern web development continues to grow, driven by its flexibility, performance, and the strong support from the community.",
        "articleImage": "https://picsum.photos/id/3/250/150",
        "articleType": "React"
      },
      {
        "id": 4,
        "authorImage": "https://encrypted-tbn0.gstatic.com/images?q=tbn:ANd9GcQBvqzyx_zoi6q2c0Gd1XnE7wysD9PGOLe3-A&s",
        "authorName": "Vone Jen",
        "publicationName": "Tech Revolution",
        "publicationDate": "06-04-2024",
        "articleTitle": "The Rise of Remote Work",
        "content": "Remote work has rapidly evolved from a niche practice to a mainstream trend, transforming how companies operate and employees work. Here’s an in-depth look at the rise of remote work: Flexibility and Work-Life Balance: Remote work offers employees greater flexibility to manage their work and personal lives. This balance leads to increased job satisfaction and productivity as employees can work in environments that suit their preferences. Cost Savings: Both employees and employers benefit from cost savings associated with remote work. Employees save on commuting expenses and work attire, while employers can reduce overhead costs by downsizing office spaces. Talent Pool Expansion: Remote work enables companies to tap into a global talent pool, hiring the best talent regardless of geographical location. This diversity brings fresh perspectives and innovation to organizations. Technology and Tools: The proliferation of communication and collaboration tools like Zoom, Slack, and Microsoft Teams has made remote work feasible and efficient. Cloud-based platforms and project management tools ensure seamless coordination and productivity. Challenges and Solutions: Remote work also presents challenges such as isolation, communication barriers, and maintaining company culture. Organizations are addressing these issues through virtual team-building activities, regular check-ins, and fostering an inclusive remote work environment. Hybrid Work Model: The hybrid work model, combining remote and in-office work, is gaining popularity. This model offers the benefits of remote work while maintaining the advantages of face-to-face collaboration. Future of Remote Work: The future of remote work looks promising, with more companies adopting flexible work arrangements. As technology continues to advance, remote work is likely to become even more integrated into the corporate landscape. Remote work is reshaping the future of work, offering flexibility, cost savings, and access to a broader talent pool.",
        "articleImage": "https://picsum.photos/id/4/250/150",
        "articleType": "Work"
      },
      {
        "id": 5,
        "authorImage": "https://encrypted-tbn0.gstatic.com/images?q=tbn:ANd9GcRkZUUzPWexwYFKYLr3eR81HIW6UGWZcAKoSQ&s",
        "authorName": "Rona Sed",
        "publicationName": "Startup Stories",
        "publicationDate": "06-05-2024",
        "articleTitle": "The Entrepreneurial Mindset",
        "content": "The entrepreneurial mindset is crucial for success in the business world, driving innovation and resilience. Here's an in-depth look at the key aspects of this mindset: Embracing Failure: Entrepreneurs view failure as a learning opportunity rather than a setback. This perspective helps them take calculated risks and innovate without the fear of making mistakes. Adaptability: The ability to adapt to changing circumstances is vital for entrepreneurs. They stay agile, pivoting their strategies and business models to meet evolving market demands. Vision and Passion: Successful entrepreneurs have a clear vision and a passion for their ventures. This passion fuels their perseverance and motivates them to overcome obstacles. Problem-Solving: Entrepreneurs are natural problem-solvers, constantly seeking solutions to challenges. They identify gaps in the market and develop products or services to address those needs. Resilience: Building a business involves facing numerous challenges and setbacks. Resilience helps entrepreneurs stay focused and committed, even in the face of adversity. Networking: Entrepreneurs understand the importance of building a strong network. They connect with mentors, investors, and other entrepreneurs to gain insights, support, and opportunities. Continuous Learning: The entrepreneurial mindset values continuous learning and self-improvement. Entrepreneurs stay informed about industry trends, seek feedback, and invest in their personal and professional development. Customer Focus: Successful entrepreneurs prioritize their customers' needs and feedback. They develop products and services that provide value and build strong customer relationships. Time Management: Effective time management is essential for entrepreneurs to balance multiple responsibilities. They prioritize tasks, delegate when necessary, and focus on activities that drive growth. The entrepreneurial mindset is about embracing challenges, staying adaptable, and continually seeking opportunities for growth and innovation.",
        "articleImage": "https://picsum.photos/id/5/250/150",
        "articleType": "Entrepreneurship"
      },
      {
        "id": 6,
        "authorImage": "https://encrypted-tbn0.gstatic.com/images?q=tbn:ANd9GcSQzqpqlCggzfyOzZjHe6hUdz44tKUPZESpkQ&s",
        "authorName": "Gems Fond",
        "publicationName": "Code Master",
        "publicationDate": "06-06-2024",
        "articleTitle": "The Power of Open Source",
        "content": "Open source software has revolutionized the tech industry, offering numerous benefits to developers and organizations. Here’s an in-depth look at the power of open source: Collaboration and Community: Open source projects foster collaboration among developers worldwide. Communities contribute to the development, improvement, and maintenance of software, driving innovation and quality. Cost Savings: Open source software is typically free to use, reducing the cost of software development and deployment. Organizations can allocate resources to other critical areas, enhancing overall efficiency. Transparency and Security: The transparency of open source code allows for thorough inspection and auditing. This visibility helps identify and address security vulnerabilities quickly, leading to more secure software. Flexibility and Customization: Open source software provides the flexibility to modify and customize code to meet specific needs. Organizations can tailor software solutions to their requirements, enhancing functionality and performance. Rapid Innovation: The collaborative nature of open source accelerates innovation. Developers can build on existing projects, share ideas, and introduce new features at a faster pace. Vendor Independence: Using open source software reduces dependency on a single vendor. Organizations have the freedom to choose and switch between solutions without being locked into proprietary systems. Skill Development: Contributing to open source projects helps developers improve their skills and gain valuable experience. It provides opportunities for learning, networking, and showcasing their expertise. Interoperability: Open source promotes interoperability and standards compliance. This ensures that different software systems can work together seamlessly, enhancing integration and functionality. Sustainability: Many open source projects are sustained by a global community of contributors. This collective effort ensures the longevity and continuous improvement of software. Open source software is a powerful force in the tech industry, driving collaboration, innovation, and cost savings.",
        "articleImage": "https://picsum.photos/id/6/250/150",
        "articleType": "Coding"
      },
      {
        "id": 7,
        "authorImage": "https://encrypted-tbn0.gstatic.com/images?q=tbn:ANd9GcTGmt7mgLLJbU_An415Sur0-Iq8kRKQzzAwCw&s",
        "authorName": "Drake Gen",
        "publicationName": "Web Weekly",
        "publicationDate": "06-07-2024",
        "articleTitle": "Building Scalable Web Applications",
        "content": "Building scalable web applications is crucial for handling growing user bases and ensuring a smooth user experience. Here’s an in-depth look at the strategies for achieving scalability: Load Balancing: Load balancing distributes incoming traffic across multiple servers, ensuring no single server is overwhelmed. This improves performance and reliability, especially during peak usage times. Caching: Implementing caching mechanisms, such as in-memory caches and content delivery networks (CDNs), reduces the load on servers and speeds up response times. Cached data is served quickly, improving user experience. Database Optimization: Optimizing database performance is key to scalability. This involves indexing, query optimization, and using distributed databases. Techniques like sharding and replication help manage large datasets efficiently. Asynchronous Processing: Asynchronous processing allows tasks to be handled in the background, freeing up resources for immediate user requests. Technologies like message queues and task schedulers facilitate asynchronous operations. Microservices Architecture: Breaking down a monolithic application into microservices improves scalability. Each microservice handles a specific functionality and can be scaled independently, enhancing flexibility and fault tolerance. Auto-scaling: Auto-scaling automatically adjusts the number of servers based on traffic demands. Cloud platforms like AWS, Azure, and Google Cloud provide auto-scaling features that ensure optimal resource utilization. Performance Monitoring: Continuous monitoring of application performance helps identify bottlenecks and areas for improvement. Tools like New Relic, Datadog, and Grafana provide insights into system health and performance metrics. Code Efficiency: Writing efficient code that minimizes resource consumption is essential for scalability. Code reviews, performance testing, and refactoring help maintain high performance standards. Security Considerations: Scalability should not compromise security. Implementing robust security measures, such as encryption, authentication, and access controls, ensures the application remains secure as it scales. Building scalable web applications involves a combination of architectural strategies, performance optimization, and continuous monitoring to ensure smooth operation under varying loads.",
        "articleImage": "https://picsum.photos/id/7/250/150",
        "articleType": "Web Development"
      },
      {
        "id": 8,
        "authorImage": "https://encrypted-tbn0.gstatic.com/images?q=tbn:ANd9GcQRqSHLPBTh2ZGuUGdL0-SMusi-DYLRutF53g&s",
        "authorName": "Sam Welle",
        "publicationName": "React Journal",
        "publicationDate": "06-08-2024",
        "articleTitle": "State Management in React",
        "content": "State management is a critical aspect of React applications, ensuring data consistency and efficient rendering. Here’s an in-depth look at state management in React: useState Hook: The useState hook is the fundamental way to manage state in functional components. It allows developers to add state variables and update them within the component. useReducer Hook: The useReducer hook is useful for managing complex state logic. It provides an alternative to useState, especially when dealing with multiple related state variables or complex state transitions. Context API: The Context API enables sharing state across the entire application or specific parts of it without prop drilling. It simplifies state management for global state, such as user authentication and theme settings. Redux: Redux is a popular state management library for larger applications. It provides a centralized store for application state and uses actions and reducers to handle state changes predictably. Recoil: Recoil is a state management library developed by Facebook for managing shared state in React applications. It offers a simpler API and better performance for certain use cases compared to Redux. MobX: MobX is another state management library that uses reactive programming principles. It automatically tracks state dependencies and re-renders components when the state changes. Zustand: Zustand is a lightweight state management library that provides a simple and flexible API. It allows for easy state management without the boilerplate code often associated with Redux. Combining Approaches: In some cases, combining multiple state management approaches can be beneficial. For example, using useState for local component state and Redux or Context API for global state. Best Practices: Best practices for state management include keeping state as minimal as possible, using derived state to avoid duplication, and avoiding unnecessary re-renders by memoizing components. State management is a crucial aspect of React development, providing the tools and patterns needed to maintain application state effectively.",
        "articleImage": "https://picsum.photos/id/8/250/150",
        "articleType": "React"
      },
      {
        "id": 9,
        "authorImage": "https://encrypted-tbn0.gstatic.com/images?q=tbn:ANd9GcRSlYVL1Z7yTyqxvmXpKLH5Ye8QrRuNC2sx2A&s",
        "authorName": "Den Wen",
        "publicationName": "Entrepreneur Today",
        "publicationDate": "06-09-2024",
        "articleTitle": "Scaling Your Startup",
        "content": "Scaling a startup is a critical phase that involves expanding operations while maintaining efficiency and quality. Here’s an in-depth look at strategies for successfully scaling your startup: Building a Strong Team: A talented and dedicated team is essential for scaling. Focus on hiring individuals who align with your company’s vision and culture, and invest in their growth and development. Streamlining Operations: Streamlining operations through process optimization and automation helps improve efficiency. Identify bottlenecks and implement solutions to enhance productivity and reduce costs. Leveraging Technology: Technology plays a crucial role in scaling. Utilize cloud computing, data analytics, and automation tools to manage and analyze data, streamline workflows, and enhance decision-making. Expanding Market Reach: Expanding into new markets can drive growth. Conduct thorough market research to identify opportunities and develop strategies for entering new regions or demographics. Securing Funding: Scaling often requires additional capital. Explore various funding options such as venture capital, angel investors, and crowdfunding to secure the necessary resources for growth. Enhancing Customer Experience: Focus on providing exceptional customer service and experiences. Happy customers are more likely to become repeat buyers and brand advocates, driving organic growth. Building Partnerships: Strategic partnerships can accelerate scaling by providing access to new customers, technologies, and resources. Collaborate with complementary businesses to expand your reach and capabilities. Maintaining Company Culture: As your startup grows, maintaining a strong company culture is vital. Foster an inclusive and positive work environment to retain top talent and keep employees motivated. Monitoring Performance: Continuously monitor key performance indicators (KPIs) to track progress and identify areas for improvement. Use data-driven insights to make informed decisions and adjust strategies as needed. Risk Management: Scaling involves risks, such as market fluctuations and operational challenges. Develop a risk management plan to mitigate potential threats and ensure business continuity. Scaling a startup requires a strategic approach, leveraging technology, building strong teams, and continuously improving processes to achieve sustainable growth.",
        "articleImage": "https://picsum.photos/id/9/250/150",
        "articleType": "Entrepreneurship"
      },
      {
        "id": 10,
        "authorImage": "https://images.pexels.com/photos/3785104/pexels-photo-3785104.jpeg?cs=srgb&dl=pexels-olly-3785104.jpg&fm=jpg",
        "authorName": "Swen Dwell",
        "publicationName": "Tech Trends",
        "publicationDate": "06-10-2024",
        "articleTitle": "Innovations in Coding Practices",
        "content": "Innovations in coding practices are continuously evolving, driving efficiency and quality in software development. Here’s an in-depth look at some of the latest trends and techniques: Test-Driven Development: Test-Driven Development (TDD) involves writing tests before code implementation. This approach ensures code reliability, improves design, and reduces the likelihood of bugs. Continuous Integration and Continuous Deployment: CI/CD practices automate the testing and deployment process, allowing developers to integrate code changes more frequently and deploy updates rapidly. This enhances productivity and reduces downtime. Pair Programming: Pair programming involves two developers working together on the same code. This practice improves code quality, facilitates knowledge sharing, and enhances problem-solving capabilities. Code Reviews: Regular code reviews help maintain code quality and consistency. They provide opportunities for feedback, catch potential issues early, and promote collaborative learning. DevOps Culture: DevOps integrates development and operations teams to improve collaboration, streamline workflows, and accelerate delivery. This cultural shift enhances efficiency and innovation in coding practices. Version Control: Version control systems like Git are essential for managing code changes, collaborating with team members, and maintaining a history of modifications. Branching and merging strategies help organize development efforts. Static Code Analysis: Static code analysis tools automatically review code for potential errors, security vulnerabilities, and adherence to coding standards. They provide immediate feedback, helping developers write cleaner code. Agile Methodologies: Agile methodologies prioritize flexibility, collaboration, and iterative development. Practices like Scrum and Kanban help teams deliver high-quality software incrementally and respond quickly to changing requirements. Coding Standards and Best Practices: Adhering to coding standards and best practices ensures code readability, maintainability, and consistency. Documenting guidelines and conducting regular training help enforce these standards. Leveraging AI in Coding: AI-powered tools assist developers in writing code, detecting bugs, and optimizing performance. These tools enhance productivity and support developers in focusing on complex tasks. Innovations in coding practices are transforming software development, driving higher quality, efficiency, and collaboration.",
        "articleImage": "https://picsum.photos/id/10/250/150",
        "articleType": "Coding"
      },
      {
        "id": 11,
        "authorImage": "https://encrypted-tbn0.gstatic.com/images?q=tbn:ANd9GcQ3wDZLZ6BecUn5rtnNEkkrApwxwhffoGGZlA&s",
        "authorName": "Jane Wilde",
        "publicationName": "Tech Insights",
        "publicationDate": "06-11-2024",
        "articleTitle": "The Future of E-Commerce",
        "content": "The future of e-commerce is set to be shaped by emerging technologies and changing consumer behaviors. Here’s an in-depth look at the trends and innovations transforming the e-commerce landscape: Artificial Intelligence: AI is revolutionizing e-commerce by enabling personalized shopping experiences, chatbots for customer service, and predictive analytics for inventory management. AI-powered recommendations enhance customer satisfaction and drive sales. Augmented Reality: AR allows customers to visualize products in their environment before purchasing. This technology is particularly useful for fashion, furniture, and home decor, reducing the rate of returns and increasing customer confidence. Mobile Commerce: With the increasing use of smartphones, mobile commerce is becoming a dominant force. Optimizing websites for mobile devices and developing dedicated apps enhances user experience and captures the growing mobile shopper market. Voice Commerce: Voice assistants like Amazon's Alexa and Google Assistant are enabling voice-activated shopping. Voice commerce simplifies the purchasing process and offers a hands-free shopping experience. Subscription Models: Subscription-based e-commerce models provide recurring revenue and foster customer loyalty. Businesses offer products or services on a subscription basis, catering to customers' preferences for convenience and personalization. Social Commerce: Social media platforms are integrating shopping features, allowing users to purchase products directly from their feeds. Social commerce leverages influencers and user-generated content to drive sales. Sustainable Practices: Eco-friendly and sustainable practices are becoming increasingly important to consumers. E-commerce businesses are adopting green initiatives, such as eco-friendly packaging and carbon-neutral shipping, to appeal to environmentally conscious shoppers. Omnichannel Retailing: Omnichannel strategies provide a seamless shopping experience across online and offline channels. Integrating brick-and-mortar stores with online platforms enhances customer convenience and satisfaction. Blockchain Technology: Blockchain ensures transparency and security in transactions. It can be used for supply chain management, ensuring product authenticity and reducing fraud. Enhanced Payment Options: Diverse payment options, including digital wallets, cryptocurrencies, and buy-now-pay-later services, cater to varying customer preferences and enhance the checkout experience. The future of e-commerce is dynamic, driven by technological advancements and evolving consumer expectations, promising a more personalized, convenient, and secure shopping experience.",
        "articleImage": "https://picsum.photos/id/11/250/150",
        "articleType": "Work"
      },
      {
        "id": 12,
        "authorImage": "https://www.davidchang.ca/wp-content/uploads/2020/09/David-Chang-Photography-Headshots-Toronto-61.jpg",
        "authorName": "Dek Sem",
        "publicationName": "Dev Journal",
        "publicationDate": "06-12-2024",
        "articleTitle": "Modern JavaScript Frameworks",
        "content": "Modern JavaScript frameworks have transformed web development, offering powerful tools for building dynamic and responsive applications. Here’s an in-depth look at some of the leading frameworks: React: Developed by Facebook, React is a popular library for building user interfaces. Its component-based architecture and virtual DOM make it efficient for creating dynamic and interactive web applications. Angular: Angular, developed by Google, is a comprehensive framework for building single-page applications. It provides a robust set of tools and features, including two-way data binding, dependency injection, and a powerful CLI. Vue.js: Vue.js is a progressive framework for building user interfaces. It is known for its simplicity and flexibility, allowing developers to incrementally adopt its features. Vue's reactivity system and component-based architecture make it easy to build complex applications. Svelte: Svelte is a relatively new framework that shifts the work to compile time, producing highly efficient code. It eliminates the virtual DOM, resulting in faster runtime performance and smaller bundle sizes. Ember.js: Ember.js is an opinionated framework for building ambitious web applications. It provides a strong convention-over-configuration philosophy, which speeds up development by enforcing best practices and reducing decision fatigue. Backbone.js: Backbone.js offers a minimalist approach to structuring web applications. It provides models, views, collections, and routers, allowing developers to build applications with a clear separation of concerns. Next.js: Next.js is a React-based framework that supports server-side rendering and static site generation. It enhances the performance and SEO of React applications and offers a seamless developer experience. Nuxt.js: Nuxt.js is a framework built on top of Vue.js, providing server-side rendering and static site generation capabilities. It simplifies the development of performant and SEO-friendly Vue applications. Aurelia: Aurelia is a modern framework that emphasizes clean code and developer productivity. It leverages ES6 features and offers a flexible and extensible platform for building web applications. Preact: Preact is a lightweight alternative to React with a similar API. It is ideal for performance-sensitive applications where reducing bundle size is critical. Modern JavaScript frameworks provide a wide range of options for developers, each offering unique features and benefits for building robust web applications.",
        "articleImage": "https://picsum.photos/id/12/250/150",
        "articleType": "Web Development"
      },
      {
        "id": 13,
        "authorImage": "https://encrypted-tbn0.gstatic.com/images?q=tbn:ANd9GcR3Rf3G8lRfHK4D5hXqhrI5LU-wZThP2MCVoQ&s",
        "authorName": "Jenny Bint",
        "publicationName": "Market Trends",
        "publicationDate": "06-13-2024",
        "articleTitle": "The Future of Cryptocurrency",
        "content": "The future of cryptocurrency is an exciting and rapidly evolving topic, with several trends and innovations shaping its trajectory. Here’s an in-depth look at what to expect: Institutional Adoption: Major financial institutions and corporations are increasingly adopting cryptocurrencies as part of their portfolios and payment systems. This mainstream acceptance is driving credibility and stability in the crypto market. Decentralized Finance (DeFi): DeFi platforms are transforming traditional financial services by offering decentralized lending, borrowing, and trading. These platforms use smart contracts to automate transactions, increasing transparency and reducing the need for intermediaries. Central Bank Digital Currencies (CBDCs): Governments worldwide are exploring the development of CBDCs to complement or replace traditional fiat currencies. CBDCs aim to enhance payment systems' efficiency and security while providing central banks with better monetary control. Blockchain Interoperability: Interoperability solutions are being developed to enable different blockchain networks to communicate and share data seamlessly. This advancement will enhance the functionality and adoption of blockchain technology. Regulatory Developments: Governments and regulatory bodies are increasingly focusing on creating clear regulations for cryptocurrencies. These regulations aim to protect investors, prevent fraud, and ensure the stability of the financial system. Sustainability Initiatives: The environmental impact of cryptocurrency mining is a growing concern. Innovations in energy-efficient mining technologies and the adoption of sustainable practices are essential for the future of cryptocurrencies. Improved Security: Enhancing the security of cryptocurrency transactions and storage remains a priority. Advances in cryptographic techniques and secure hardware wallets are helping to protect users from theft and hacking. Enhanced Privacy: Privacy-focused cryptocurrencies and technologies are being developed to offer users greater anonymity and control over their data. These innovations address concerns about surveillance and data breaches. Tokenization of Assets: The tokenization of real-world assets, such as real estate and commodities, is gaining traction. This process involves creating digital tokens representing ownership of physical assets, making them more accessible and tradable. Integration with Traditional Finance: The integration of cryptocurrencies with traditional financial systems is becoming more seamless. Payment processors, banks, and fintech companies are increasingly offering crypto-related services, bridging the gap between the crypto and fiat worlds. The future of cryptocurrency is set to be dynamic and transformative, driven by technological advancements, regulatory developments, and increasing mainstream acceptance.",
        "articleImage": "https://picsum.photos/id/13/250/150",
        "articleType": "Cryptocurrency"
      },
      {
        "id": 14,
        "authorImage": "https://encrypted-tbn0.gstatic.com/images?q=tbn:ANd9GcSfx2QK7Hb8OD8Gz7csG_2dTxJ5coF6fIj5Lg&s",
        "authorName": "Jon Witz",
        "publicationName": "Market Watch",
        "publicationDate": "06-14-2024",
        "articleTitle": "The Impact of AI on Marketing",
        "content": "Artificial intelligence is revolutionizing the marketing industry, offering unprecedented opportunities for personalization, efficiency, and insights. Here’s an in-depth look at the impact of AI on marketing: Personalized Customer Experiences: AI enables hyper-personalization by analyzing customer data and behavior. Marketers can deliver tailored content, product recommendations, and offers, enhancing customer satisfaction and loyalty. Predictive Analytics: AI-powered predictive analytics helps marketers anticipate customer needs and behaviors. This allows for proactive strategies, such as targeted campaigns and inventory management, improving conversion rates and reducing costs. Chatbots and Virtual Assistants: AI-driven chatbots and virtual assistants provide instant customer support and engagement. They handle inquiries, guide users through purchasing processes, and collect valuable data for further analysis. Content Generation: AI tools can generate high-quality content, such as blog posts, social media updates, and product descriptions. This saves time for marketers and ensures a consistent content output. Audience Segmentation: AI enhances audience segmentation by identifying patterns and trends in data. Marketers can create more precise segments, leading to more effective targeting and higher ROI. Sentiment Analysis: AI-powered sentiment analysis tools assess customer opinions and emotions from social media, reviews, and feedback. This provides valuable insights into brand perception and areas for improvement. Automated Campaigns: AI automates campaign management, from ad placement to budget allocation. Machine learning algorithms optimize campaigns in real-time, maximizing performance and efficiency. Visual Recognition: AI-based visual recognition technology analyzes images and videos to extract valuable information. This helps in understanding customer preferences and creating visually appealing content. Customer Journey Mapping: AI tracks and analyzes the customer journey across multiple touchpoints. Marketers can identify pain points, optimize user experiences, and improve customer retention. Fraud Detection: AI helps in detecting and preventing fraudulent activities, such as fake reviews and ad fraud. This ensures the integrity of marketing efforts and protects brand reputation. AI is transforming marketing by providing powerful tools for personalization, efficiency, and insights. Marketers who leverage AI can create more effective strategies, enhance customer experiences, and stay competitive in a rapidly evolving landscape.",
        "articleImage": "https://picsum.photos/id/14/250/150",
        "articleType": "Marketing"
      },
      {
        "id": 15,
        "authorImage": "https://images.pexels.com/photos/2182970/pexels-photo-2182970.jpeg?cs=srgb&dl=pexels-linkedin-2182970.jpg&fm=jpg",
        "authorName": "Farah Sen",
        "publicationName": "Tech Digest",
        "publicationDate": "06-15-2024",
        "articleTitle": "Advancements in Robotic Process Automation",
        "content": "Robotic Process Automation (RPA) is transforming business operations by automating repetitive tasks. Here’s an in-depth look at the latest advancements: Enhanced Automation Capabilities: RPA tools now integrate AI to handle complex processes, improving accuracy and efficiency. Cognitive Automation: Cognitive RPA leverages AI to understand unstructured data, enabling automation of tasks that require decision-making. Integration with Enterprise Systems: Modern RPA solutions seamlessly integrate with existing enterprise systems, enhancing data flow and reducing manual interventions. Scalability: RPA platforms offer scalable solutions, allowing businesses to automate more processes as they grow. Improved User Interfaces: User-friendly interfaces make it easier for non-technical users to design and deploy automation workflows. Enhanced Security: Advanced security features protect sensitive data during automation processes. Analytics and Reporting: Built-in analytics provide insights into process performance, helping optimize operations. Enhanced Collaboration: Collaborative tools enable teams to work together on automation projects, sharing insights and best practices. RPA is revolutionizing the way businesses operate, driving efficiency, and enabling innovation.",
        "articleImage": "https://picsum.photos/id/15/250/150",
        "articleType": "Work"
      },
      {
        "id": 16,
        "authorImage": "https://encrypted-tbn0.gstatic.com/images?q=tbn:ANd9GcQBvqzyx_zoi6q2c0Gd1XnE7wysD9PGOLe3-A&s",
        "authorName": "Vone Jen",
        "publicationName": "Web Dev News",
        "publicationDate": "06-16-2024",
        "articleTitle": "Progressive Web Apps: The Future of Mobile",
        "content": "Progressive Web Apps (PWAs) are revolutionizing mobile experiences by combining the best of web and mobile apps. Here’s an in-depth look at their benefits: Offline Access: PWAs offer offline capabilities, ensuring seamless access even without an internet connection. Improved Performance: PWAs load faster and perform better, providing a smooth user experience. Cross-Platform Compatibility: PWAs work on any device with a web browser, reducing the need for separate mobile and desktop versions. Cost-Effective Development: Developing a PWA is more cost-effective than creating native apps for multiple platforms. Enhanced User Engagement: Features like push notifications keep users engaged and informed. Security: PWAs use HTTPS to ensure secure data transmission. Easy Updates: PWAs are updated automatically, ensuring users always have the latest version. Discoverability: PWAs can be discovered through search engines, increasing visibility. PWAs are the future of mobile, offering enhanced performance, engagement, and accessibility.",
        "articleImage": "https://picsum.photos/id/16/250/150",
        "articleType": "Web Development"
      },
      {
        "id": 17,
        "authorImage": "https://encrypted-tbn0.gstatic.com/images?q=tbn:ANd9GcRkZUUzPWexwYFKYLr3eR81HIW6UGWZcAKoSQ&s",
        "authorName": "Rona Sed",
        "publicationName": "Entrepreneur's Guide",
        "publicationDate": "06-17-2024",
        "articleTitle": "Navigating Startup Funding",
        "content": "Securing funding is a critical step for startups. Here’s an in-depth look at strategies for navigating the funding landscape: Bootstrapping: Using personal savings and reinvesting profits helps maintain control but may limit growth. Angel Investors: These early-stage investors provide capital in exchange for equity, offering valuable mentorship and connections. Venture Capital: VC firms invest larger sums in exchange for equity, driving rapid growth but often requiring significant ownership and control. Crowdfunding: Platforms like Kickstarter and Indiegogo allow startups to raise small amounts from many backers, validating ideas and generating buzz. Government Grants: Various programs offer grants to support innovation and entrepreneurship, providing non-dilutive funding. Incubators and Accelerators: These programs offer funding, mentorship, and resources in exchange for equity, helping startups grow quickly. Strategic Partnerships: Partnering with established companies can provide funding, resources, and market access. Loans: Traditional bank loans or alternative financing options provide debt-based funding without diluting ownership. Navigating startup funding requires understanding the pros and cons of each option, aligning them with your business goals and growth strategy.",
        "articleImage": "https://picsum.photos/id/17/250/150",
        "articleType": "Entrepreneurship"
      },
      {
        "id": 18,
        "authorImage": "https://encrypted-tbn0.gstatic.com/images?q=tbn:ANd9GcSQzqpqlCggzfyOzZjHe6hUdz44tKUPZESpkQ&s",
        "authorName": "Gems Fond",
        "publicationName": "Tech Evolution",
        "publicationDate": "06-18-2024",
        "articleTitle": "Artificial Intelligence in Cybersecurity",
        "content": "Artificial intelligence is transforming cybersecurity by enhancing threat detection and response. Here’s an in-depth look at its impact: Threat Detection: AI analyzes vast amounts of data to identify patterns and anomalies indicative of cyber threats, improving detection rates. Automated Response: AI-powered systems can automatically respond to threats, reducing response times and mitigating damage. Predictive Analytics: AI predicts potential security breaches by analyzing historical data and identifying vulnerabilities. Behavioral Analysis: AI monitors user behavior to detect unusual activities that may indicate a security threat. Enhanced Authentication: AI improves authentication processes by analyzing biometric data and detecting fraudulent activities. Phishing Prevention: AI identifies and blocks phishing attempts by analyzing email content and sender behavior. Incident Analysis: AI helps in post-incident analysis, providing insights into the nature and impact of security breaches. Continuous Learning: AI systems continuously learn from new data, improving their ability to detect and respond to emerging threats. AI is revolutionizing cybersecurity, providing advanced tools to protect against evolving cyber threats.",
        "articleImage": "https://picsum.photos/id/18/250/150",
        "articleType": "Work"
      },
      {
        "id": 19,
        "authorImage": "https://encrypted-tbn0.gstatic.com/images?q=tbn:ANd9GcTGmt7mgLLJbU_An415Sur0-Iq8kRKQzzAwCw&s",
        "authorName": "Drake Gen",
        "publicationName": "Coding Today",
        "publicationDate": "06-19-2024",
        "articleTitle": "The Rise of Serverless Architecture",
        "content": "Serverless architecture is transforming how applications are developed and deployed. Here’s an in-depth look at its benefits: Cost Efficiency: Serverless models reduce costs by charging only for actual usage, eliminating the need for idle server time. Scalability: Serverless applications automatically scale to handle varying loads, ensuring consistent performance. Simplified Management: Developers focus on writing code without managing infrastructure, reducing operational complexity. Faster Deployment: Serverless services enable rapid deployment, allowing for quicker iteration and innovation. Enhanced Security: Cloud providers manage security, ensuring compliance with the latest standards and reducing vulnerabilities. Event-Driven Processing: Serverless architecture excels in event-driven scenarios, automatically executing code in response to events. Resource Optimization: Serverless models optimize resource utilization, providing efficiency and sustainability. Microservices Integration: Serverless architecture supports microservices, allowing for modular and maintainable application development. The rise of serverless architecture offers a new paradigm for developing scalable, cost-effective, and efficient applications.",
        "articleImage": "https://picsum.photos/id/19/250/150",
        "articleType": "Coding"
      },
      {
        "id": 20,
        "authorImage": "https://encrypted-tbn0.gstatic.com/images?q=tbn:ANd9GcQRqSHLPBTh2ZGuUGdL0-SMusi-DYLRutF53g&s",
        "authorName": "Sam Welle",
        "publicationName": "Entrepreneur Weekly",
        "publicationDate": "06-20-2024",
        "articleTitle": "The Power of Networking for Entrepreneurs",
        "content": "Networking is a crucial element for entrepreneurial success. Here’s an in-depth look at the benefits of effective networking: Building Relationships: Networking helps build strong relationships with potential clients, partners, and investors. Knowledge Sharing: Engaging with other entrepreneurs and industry experts provides valuable insights and knowledge. Opportunities: Networking opens doors to new opportunities, including partnerships, collaborations, and funding. Mentorship: Connecting with experienced entrepreneurs provides mentorship and guidance, helping navigate challenges. Brand Visibility: Networking enhances brand visibility, increasing recognition and credibility in the industry. Market Insights: Engaging with peers provides insights into market trends, customer needs, and industry developments. Support System: A strong network provides emotional and professional support, helping entrepreneurs stay motivated. Resource Access: Networking connects entrepreneurs with resources, such as talent, technology, and funding. Collaboration: Networking fosters collaboration, enabling entrepreneurs to leverage each other’s strengths. Networking is a powerful tool for entrepreneurs, providing opportunities, insights, and support essential for success.",
        "articleImage": "https://picsum.photos/id/20/250/150",
        "articleType": "Entrepreneurship"
      },
      {
        "id": 21,
        "authorImage": "https://encrypted-tbn0.gstatic.com/images?q=tbn:ANd9GcRSlYVL1Z7yTyqxvmXpKLH5Ye8QrRuNC2sx2A&s",
        "authorName": "Den Wen",
        "publicationName": "React Dev Journal",
        "publicationDate": "06-21-2024",
        "articleTitle": "React Hooks: A Game Changer in Development",
        "content": "React Hooks have revolutionized front-end development by simplifying state management and side effects. Here’s an in-depth look at their benefits: Simplified State Management: Hooks provide a simpler way to manage state in functional components, reducing boilerplate code. Reusable Logic: Hooks enable the reuse of stateful logic across components, improving code maintainability. Improved Readability: Code written with Hooks is often more readable and easier to understand. Enhanced Composition: Hooks enhance the composition of component logic, promoting modular and organized code. Side Effects Handling: The useEffect Hook provides a clear way to handle side effects, such as data fetching and subscriptions. Custom Hooks: Developers can create custom Hooks to encapsulate and reuse complex logic, promoting code reusability. Reduced Complexity: Hooks reduce the complexity of class components, making it easier to manage component lifecycles. Improved Testing: Functional components with Hooks are easier to test, enhancing code quality and reliability. React Hooks have transformed front-end development, providing powerful tools for managing state and side effects in a more efficient and readable way.",
        "articleImage": "https://picsum.photos/id/21/250/150",
        "articleType": "React"
      },
      {
        "id": 22,
        "authorImage": "https://images.pexels.com/photos/3785104/pexels-photo-3785104.jpeg?cs=srgb&dl=pexels-olly-3785104.jpg&fm=jpg",
        "authorName": "Swen Dwell",
        "publicationName": "Work Smarter",
        "publicationDate": "06-22-2024",
        "articleTitle": "Time Management Tips for Remote Workers",
        "content": "Effective time management is crucial for remote workers to maintain productivity and work-life balance. Here’s an in-depth look at essential tips: Set a Schedule: Establishing a consistent schedule helps create a routine and set boundaries between work and personal life. Prioritize Tasks: Prioritize tasks based on importance and deadlines to ensure critical work is completed first. Use Time Management Tools: Utilize tools like calendars, to-do lists, and time-tracking apps to organize and monitor tasks. Create a Dedicated Workspace: A dedicated workspace minimizes distractions and enhances focus. Take Regular Breaks: Regular breaks prevent burnout and maintain productivity. Follow the Pomodoro Technique: Work in focused intervals, followed by short breaks, to boost concentration and efficiency. Avoid Multitasking: Focus on one task at a time to improve quality and efficiency. Set Clear Boundaries: Communicate boundaries with family and friends to minimize interruptions during work hours. Reflect and Adjust: Regularly assess your time management strategies and make adjustments as needed. Time management is key to remote work success, helping maintain productivity, reduce stress, and achieve a better work-life balance.",
        "articleImage": "https://picsum.photos/id/22/250/150",
        "articleType": "Work"
      },
      {
        "id": 23,
        "authorImage": "https://encrypted-tbn0.gstatic.com/images?q=tbn:ANd9GcQ3wDZLZ6BecUn5rtnNEkkrApwxwhffoGGZlA&s",
        "authorName": "Jane Wilde",
        "publicationName": "Web Tech",
        "publicationDate": "06-23-2024",
        "articleTitle": "The Evolution of Web Development Frameworks",
        "content": "Web development frameworks have evolved significantly, offering powerful tools for building modern applications. Here’s an in-depth look at their evolution: Early Frameworks: Early frameworks like Ruby on Rails and Django simplified web development by providing pre-built modules and conventions. JavaScript Frameworks: The rise of JavaScript frameworks like Angular, React, and Vue.js revolutionized front-end development, offering component-based architectures. Progressive Frameworks: Progressive frameworks like Svelte and Next.js focus on performance and developer experience, enhancing the efficiency of modern web applications. Static Site Generators: Static site generators like Gatsby and Hugo offer fast and secure websites, ideal for content-driven sites. Full-Stack Frameworks: Full-stack frameworks like Meteor and Next.js enable seamless development across the front and back end. Mobile-First Frameworks: Frameworks like Ionic and React Native allow for the development of mobile applications using web technologies. Microservices Architecture: Modern frameworks support microservices architecture, promoting modularity and scalability. Low-Code/No-Code Solutions: Emerging low-code and no-code frameworks democratize web development, enabling non-technical users to build applications. The evolution of web development frameworks continues to enhance efficiency, performance, and accessibility in building modern applications.",
        "articleImage": "https://picsum.photos/id/23/250/150",
        "articleType": "Web Development"
      },
      {
        "id": 24,
        "authorImage": "https://www.davidchang.ca/wp-content/uploads/2020/09/David-Chang-Photography-Headshots-Toronto-61.jpg",
        "authorName": "Dek Sem",
        "publicationName": "Entrepreneur Insights",
        "publicationDate": "06-24-2024",
        "articleTitle": "Building a Sustainable Business Model",
        "content": "Sustainability is becoming a core component of successful business models. Here’s an in-depth look at how to build a sustainable business model: Define Your Mission: Establish a clear mission that incorporates sustainability as a core value. Eco-Friendly Practices: Implement eco-friendly practices in operations, such as reducing waste, conserving energy, and using sustainable materials. Sustainable Supply Chain: Partner with suppliers who adhere to sustainable practices, ensuring ethical sourcing and production. Product Design: Design products with sustainability in mind, using recyclable or biodegradable materials and minimizing environmental impact. Energy Efficiency: Invest in energy-efficient technologies and processes to reduce your carbon footprint. Social Responsibility: Engage in socially responsible activities, such as supporting community initiatives and fair labor practices. Transparency: Maintain transparency with stakeholders about your sustainability efforts and progress. Innovation: Continuously innovate to find new ways to improve sustainability and reduce environmental impact. Customer Engagement: Educate and engage customers on the importance of sustainability and how they can contribute. Measure and Report: Regularly measure and report on your sustainability efforts, using data to drive improvements. Building a sustainable business model is not only good for the planet but also enhances brand reputation, customer loyalty, and long-term success.",
        "articleImage": "https://picsum.photos/id/24/250/150",
        "articleType": "Entrepreneurship"
      },
      {
        "id": 25,
        "authorImage": "https://images.pexels.com/photos/2182970/pexels-photo-2182970.jpeg?cs=srgb&dl=pexels-linkedin-2182970.jpg&fm=jpg",
        "authorName": "Farah Sen",
        "publicationName": "Coding Trends",
        "publicationDate": "06-25-2024",
        "articleTitle": "The Role of AI in Software Development",
        "content": "Artificial intelligence is playing an increasingly significant role in software development. Here’s an in-depth look at its impact: Code Generation: AI-powered tools can generate code snippets or entire functions, reducing development time. Bug Detection: AI algorithms analyze code to identify and predict bugs, improving software quality. Automated Testing: AI automates testing processes, enhancing efficiency and accuracy in identifying issues. Predictive Maintenance: AI predicts when software components may fail, enabling proactive maintenance and reducing downtime. Natural Language Processing: AI-driven NLP tools assist in understanding and generating human language, improving user interfaces and documentation. Customization: AI customizes software experiences based on user behavior and preferences, enhancing user satisfaction. Code Refactoring: AI helps refactor code, optimizing performance and maintainability. Collaboration: AI facilitates collaboration by suggesting improvements and automating repetitive tasks. Security: AI enhances security by identifying vulnerabilities and suggesting mitigation strategies. AI is transforming software development, offering tools and techniques that enhance efficiency, quality, and innovation.",
        "articleImage": "https://picsum.photos/id/25/250/150",
        "articleType": "Coding"
      },
      {
        "id": 26,
        "authorImage": "https://encrypted-tbn0.gstatic.com/images?q=tbn:ANd9GcQBvqzyx_zoi6q2c0Gd1XnE7wysD9PGOLe3-A&s",
        "authorName": "Vone Jen",
        "publicationName": "Web Today",
        "publicationDate": "06-26-2024",
        "articleTitle": "The Importance of Responsive Design",
        "content": "Responsive design is essential for providing a seamless user experience across devices. Here’s an in-depth look at its importance: User Experience: Responsive design ensures a consistent and user-friendly experience on all devices, enhancing satisfaction and engagement. Mobile Traffic: With increasing mobile traffic, responsive design is crucial for reaching and retaining mobile users. SEO Benefits: Search engines favor responsive websites, improving search rankings and visibility. Cost Efficiency: Developing a single responsive site is more cost-effective than creating separate versions for desktop and mobile. Improved Conversion Rates: A seamless experience across devices leads to higher conversion rates and sales. Faster Load Times: Responsive design optimizes load times on all devices, reducing bounce rates and improving user retention. Future-Proofing: Responsive design adapts to new devices and screen sizes, future-proofing your website. Increased Reach: Responsive design ensures accessibility for users with different devices, expanding your audience reach. Analytics: Unified analytics across devices provide a clearer picture of user behavior and preferences. Competitive Advantage: A well-designed responsive site sets you apart from competitors and enhances your brand’s reputation. Responsive design is critical for delivering a seamless user experience, improving SEO, and driving business success.",
        "articleImage": "https://picsum.photos/id/26/250/150",
        "articleType": "Web Development"
      },
      {
        "id": 27,
        "authorImage": "https://encrypted-tbn0.gstatic.com/images?q=tbn:ANd9GcRkZUUzPWexwYFKYLr3eR81HIW6UGWZcAKoSQ&s",
        "authorName": "Rona Sed",
        "publicationName": "Business Innovators",
        "publicationDate": "06-27-2024",
        "articleTitle": "Harnessing Big Data for Business Growth",
        "content": "Big data is a powerful tool for driving business growth. Here’s an in-depth look at how to harness its potential: Data Collection: Collecting data from various sources, such as customer interactions, social media, and market trends, provides valuable insights. Data Analysis: Advanced analytics tools help interpret data, identifying patterns and trends that inform business decisions. Customer Insights: Big data provides insights into customer behavior and preferences, enabling personalized marketing and improved customer experiences. Operational Efficiency: Data analysis identifies inefficiencies and areas for improvement, streamlining operations and reducing costs. Predictive Analytics: Predictive models forecast future trends and customer behaviors, helping businesses stay ahead of the curve. Risk Management: Big data helps identify and mitigate risks, improving decision-making and reducing uncertainties. Innovation: Data-driven insights drive innovation, leading to the development of new products and services. Competitive Advantage: Leveraging big data provides a competitive edge, enabling businesses to outperform rivals. Real-Time Decision Making: Real-time data analysis supports quick, informed decision-making, enhancing agility. Compliance: Big data helps ensure compliance with regulations by providing detailed records and audit trails. Harnessing big data drives business growth by providing insights, improving efficiency, and fostering innovation.",
        "articleImage": "https://picsum.photos/id/27/250/150",
        "articleType": "Work"
      },
      {
        "id": 28,
        "authorImage": "https://encrypted-tbn0.gstatic.com/images?q=tbn:ANd9GcSQzqpqlCggzfyOzZjHe6hUdz44tKUPZESpkQ&s",
        "authorName": "Gems Fond",
        "publicationName": "React Devs",
        "publicationDate": "06-28-2024",
        "articleTitle": "State Management in React Applications",
        "content": "Effective state management is crucial for building robust React applications. Here’s an in-depth look at popular state management solutions: React's useState: The built-in useState Hook is ideal for managing local component state. Context API: The Context API provides a way to pass data through the component tree without prop drilling, suitable for global state. Redux: Redux is a popular library for managing complex application state, offering a predictable state container. MobX: MobX provides a simple and scalable state management solution with observables and reactions. Recoil: Recoil is a new state management library for React, offering fine-grained control over state. Zustand: Zustand is a small, fast, and scalable state management solution with minimal boilerplate. Jotai: Jotai provides a primitive and flexible state management solution for React applications. XState: XState manages state with finite state machines and statecharts, ideal for complex state logic. Effector: Effector is a reactive state manager for predictable state management and data flow. Zustand: Zustand is a small, fast, and scalable state management solution with minimal boilerplate. Effective state management ensures React applications are maintainable, scalable, and perform well.",
        "articleImage": "https://picsum.photos/id/28/250/150",
        "articleType": "React"
      },
      {
        "id": 29,
        "authorImage": "https://encrypted-tbn0.gstatic.com/images?q=tbn:ANd9GcTGmt7mgLLJbU_An415Sur0-Iq8kRKQzzAwCw&s",
        "authorName": "Drake Gen",
        "publicationName": "Tech Leaders",
        "publicationDate": "06-29-2024",
        "articleTitle": "The Impact of Blockchain on Data Security",
        "content": "Blockchain technology is revolutionizing data security by offering decentralized and tamper-proof solutions. Here’s an in-depth look at its impact: Decentralization: Blockchain’s decentralized nature eliminates single points of failure, enhancing data security. Immutability: Once data is recorded on the blockchain, it cannot be altered, ensuring integrity and preventing fraud. Transparency: Blockchain provides a transparent ledger, allowing all participants to verify transactions and data integrity. Enhanced Privacy: Blockchain enables secure and private data transactions, protecting sensitive information. Smart Contracts: Smart contracts automate and enforce agreements, reducing the risk of human error and fraud. Supply Chain Security: Blockchain enhances supply chain security by providing an immutable record of product history and provenance. Secure Identity Management: Blockchain offers secure identity management solutions, reducing identity theft and fraud. Data Provenance: Blockchain provides a clear record of data origins, ensuring authenticity and traceability. Regulatory Compliance: Blockchain helps ensure compliance with data protection regulations by providing detailed audit trails. Financial Security: Blockchain secures financial transactions, reducing the risk of fraud and enhancing trust. Blockchain technology is transforming data security, offering robust solutions for integrity, privacy, and transparency.",
        "articleImage": "https://picsum.photos/id/29/250/150",
        "articleType": "Work"
      },
      {
        "id": 30,
        "authorImage": "https://encrypted-tbn0.gstatic.com/images?q=tbn:ANd9GcQRqSHLPBTh2ZGuUGdL0-SMusi-DYLRutF53g&s",
        "authorName": "Sam Welle",
        "publicationName": "Entrepreneur Daily",
        "publicationDate": "06-30-2024",
        "articleTitle": "Building a Strong Brand Identity",
        "content": "A strong brand identity is crucial for business success. Here’s an in-depth look at how to build and maintain a powerful brand identity: Define Your Brand: Clearly define your brand’s mission, vision, and values to create a solid foundation. Consistent Messaging: Ensure consistency in messaging across all platforms to build trust and recognition. Visual Identity: Develop a cohesive visual identity, including logo, color scheme, and typography, that reflects your brand’s personality. Storytelling: Use storytelling to connect with your audience emotionally and convey your brand’s unique story. Customer Experience: Deliver a consistent and positive customer experience to build loyalty and trust. Market Positioning: Position your brand strategically in the market to differentiate it from competitors. Brand Voice: Establish a distinct brand voice that resonates with your target audience. Social Media Presence: Leverage social media to engage with your audience and reinforce your brand identity. Employee Advocacy: Encourage employees to become brand advocates, promoting your brand’s values and mission. Monitor and Adapt: Regularly monitor your brand’s performance and adapt strategies to stay relevant. Building a strong brand identity enhances recognition, loyalty, and long-term success.",
        "articleImage": "https://picsum.photos/id/30/250/150",
        "articleType": "Entrepreneurship"
      },
      {
        "id": 31,
        "authorImage": "https://encrypted-tbn0.gstatic.com/images?q=tbn:ANd9GcRSlYVL1Z7yTyqxvmXpKLH5Ye8QrRuNC2sx2A&s",
        "authorName": "Den Wen",
        "publicationName": "React Trends",
        "publicationDate": "07-01-2024",
        "articleTitle": "Optimizing Performance in React Applications",
        "content": "Optimizing performance is crucial for delivering fast and responsive React applications. Here’s an in-depth look at key strategies: Code Splitting: Use code splitting to break up large bundles, improving initial load times and reducing latency. Lazy Loading: Implement lazy loading to load components and resources only when needed, enhancing performance. Memoization: Use React’s memoization techniques, like useMemo and React.memo, to prevent unnecessary re-renders. Virtualization: Implement virtualization with libraries like React Virtualized to efficiently render large lists and grids. State Management: Optimize state management by minimizing state updates and using efficient state management solutions. Server-Side Rendering: Implement server-side rendering (SSR) to improve performance and SEO for React applications. Use Hooks Wisely: Avoid unnecessary state and effect Hooks that can cause performance issues. Optimize Images: Compress and optimize images to reduce load times and improve performance. Web Vitals: Monitor and improve key web vitals, such as LCP, FID, and CLS, to enhance user experience. Performance Testing: Regularly test and profile your application to identify and address performance bottlenecks. Optimizing performance ensures React applications are fast, responsive, and provide an excellent user experience.",
        "articleImage": "https://picsum.photos/id/31/250/150",
        "articleType": "React"
      },
      {
        "id": 32,
        "authorImage": "https://images.pexels.com/photos/3785104/pexels-photo-3785104.jpeg?cs=srgb&dl=pexels-olly-3785104.jpg&fm=jpg",
        "authorName": "Swen Dwell",
        "publicationName": "Work Smart",
        "publicationDate": "07-02-2024",
        "articleTitle": "Strategies for Effective Team Collaboration",
        "content": "Effective team collaboration is essential for achieving business goals and driving innovation. Here’s an in-depth look at key strategies: Clear Communication: Establish clear communication channels to ensure everyone is on the same page. Set Goals: Define clear and achievable goals to provide direction and motivation for the team. Roles and Responsibilities: Clearly define roles and responsibilities to avoid confusion and overlap. Use Collaboration Tools: Utilize tools like project management software, chat platforms, and file-sharing services to enhance collaboration. Foster Trust: Build trust within the team by promoting transparency, respect, and accountability. Encourage Feedback: Create an environment where team members feel comfortable providing and receiving feedback. Regular Meetings: Hold regular meetings to discuss progress, address issues, and align on goals. Celebrate Success: Acknowledge and celebrate team achievements to boost morale and motivation. Adaptability: Encourage adaptability and flexibility to respond to changing circumstances and challenges. Continuous Improvement: Promote a culture of continuous improvement by encouraging learning and development. Effective team collaboration drives productivity, innovation, and success, creating a positive and dynamic work environment.",
        "articleImage": "https://picsum.photos/id/32/250/150",
        "articleType": "Work"
      },
      {
        "id": 33,
        "authorImage": "https://images.pexels.com/photos/2182970/pexels-photo-2182970.jpeg?cs=srgb&dl=pexels-linkedin-2182970.jpg&fm=jpg",
        "authorName": "Farah Sen",
        "publicationName": "Developer Today",
        "publicationDate": "07-03-2024",
        "articleTitle": "The Future of Software Development",
        "content": "The future of software development is being shaped by emerging technologies and changing paradigms. Here’s an in-depth look at key trends: AI and Machine Learning: AI and machine learning are automating tasks, enhancing decision-making, and creating intelligent applications. Quantum Computing: Quantum computing promises to revolutionize problem-solving with unprecedented computational power. Edge Computing: Edge computing is enabling real-time data processing closer to the source, improving performance and reducing latency. Low-Code/No-Code Platforms: These platforms are democratizing software development, allowing non-developers to create applications. DevOps and Continuous Delivery: DevOps practices are enhancing collaboration, automation, and efficiency in software development. Blockchain: Blockchain technology is providing secure, decentralized solutions for various applications. Augmented Reality (AR) and Virtual Reality (VR): AR and VR are creating immersive experiences for gaming, training, and other applications. Cybersecurity: As threats evolve, cybersecurity remains a critical focus, with advanced tools and practices to protect software. Cloud-Native Development: Cloud-native development is leveraging the power of cloud computing to build scalable and resilient applications. Ethical AI: The focus on ethical AI is growing, ensuring that AI systems are fair, transparent, and accountable. The future of software development is dynamic and exciting, driven by technological advancements and innovative approaches.",
        "articleImage": "https://picsum.photos/id/33/250/150",
        "articleType": "Coding"
      }
    ]
     }